pyblue/__init__.py
pyblue/__main__.py
pyblue/engine.py
pyblue/links.py
pyblue/pyblue
pyblue/__pycache__/__init__.cpython-38.pyc
pyblue/__pycache__/engine.cpython-38.pyc
pyblue/templates/bookdown.html
pyblue/templates/pyblue_assets.html
pyblue/templates/pyblue_base.html
pyblue/templates/pyblue_code.html
pyblue/templates/pyblue_content.html
pyblue/templates/pyblue_hello.html
pyblue/templates/pyblue_img.html
pyblue/templates/pyblue_link.html
pyblue/templates/pyblue_markdown.html
pyblue/templates/pyblue_thumb.html
pyblue/templatetags/__init__.py
pyblue/templatetags/pytags.py
pyblue/templatetags/__pycache__/__init__.cpython-38.pyc
pyblue/templatetags/__pycache__/pytags.cpython-38.pyc
pyblue-2022.8.1.data/data/pyblue/templates/bookdown.html
pyblue-2022.8.1.data/data/pyblue/templates/pyblue_assets.html
pyblue-2022.8.1.data/data/pyblue/templates/pyblue_base.html
pyblue-2022.8.1.data/data/pyblue/templates/pyblue_code.html
pyblue-2022.8.1.data/data/pyblue/templates/pyblue_content.html
pyblue-2022.8.1.data/data/pyblue/templates/pyblue_hello.html
pyblue-2022.8.1.data/data/pyblue/templates/pyblue_img.html
pyblue-2022.8.1.data/data/pyblue/templates/pyblue_link.html
pyblue-2022.8.1.data/data/pyblue/templates/pyblue_markdown.html
pyblue-2022.8.1.data/data/pyblue/templates/pyblue_thumb.html
pyblue-2022.8.1.data/scripts/pyblue
pyblue-2022.8.1.dist-info/LICENSE.txt
pyblue-2022.8.1.dist-info/METADATA
pyblue-2022.8.1.dist-info/WHEEL
pyblue-2022.8.1.dist-info/top_level.txt
pyblue-2022.8.1.dist-info/RECORD
