Metadata-Version: 2.1
Name: pyblue
Version: 2022.8.1
Summary: PyBlue
Home-page: https://github.com/ialbert/pyblue
Author: Istvan Albert
Author-email: istvan.albert@gmail.com
License: MIT
Classifier: Development Status :: 5 - Production/Stable
Classifier: Environment :: Console
Classifier: Environment :: Web Environment
Classifier: Intended Audience :: End Users/Desktop
Classifier: Intended Audience :: Developers
Classifier: Intended Audience :: Education
Classifier: License :: OSI Approved :: MIT License
Classifier: Operating System :: MacOS :: MacOS X
Classifier: Operating System :: Microsoft :: Windows
Classifier: Operating System :: POSIX
Classifier: Programming Language :: Python :: 2.7
Classifier: Programming Language :: Python :: 3.1
Classifier: Programming Language :: Python :: 3.2
Classifier: Programming Language :: Python :: 3.3
Classifier: Programming Language :: Python :: 3.4
Classifier: Topic :: Internet :: WWW/HTTP :: Dynamic Content
Classifier: Topic :: Scientific/Engineering :: Bio-Informatics
License-File: LICENSE.txt
Requires-Dist: django (==1.11.23)
Requires-Dist: bottle
Requires-Dist: commonmark (==0.9.1)
Requires-Dist: markdown-it-py[plugins]
Requires-Dist: waitress (==1.4.3)
Requires-Dist: bleach (==3.3.0)
Requires-Dist: bs4
